teleinfo/__init__.py
teleinfo/base_vendor.py
teleinfo/hw_vendors.py
teleinfo/parser.py
teleinfo/sw_vendors.py
teleinfo/utils.py
teleinfo-1.3.1.dist-info/LICENSE
teleinfo-1.3.1.dist-info/METADATA
teleinfo-1.3.1.dist-info/WHEEL
teleinfo-1.3.1.dist-info/entry_points.txt
teleinfo-1.3.1.dist-info/top_level.txt
teleinfo-1.3.1.dist-info/RECORD
