Metadata-Version: 2.1
Name: teleinfo
Version: 1.3.1
Summary: EDF Teleinfo frame acquisition
Home-page: http://github.com/demikl/python-teleinfo
Author: Mickael Le Baillif
Author-email: mickael.le.baillif@gmail.com
License: MIT
Platform: UNKNOWN
Classifier: Development Status :: 3 - Alpha
Classifier: Intended Audience :: Developers
Classifier: Intended Audience :: Information Technology
Classifier: License :: OSI Approved :: MIT License
Classifier: Operating System :: POSIX :: Linux
Classifier: Programming Language :: Python
Classifier: Topic :: Home Automation
Classifier: Topic :: Software Development :: Libraries :: Python Modules
License-File: LICENSE
Requires-Dist: pyserial
